{"nodes":[{"id":"1453b11a-006e-4670-9fb7-7f8467904965","name":"MENU","physics":false,"type":"entity-strong","backgroundColor":"#97C2FC","labelColor":"#000000","x":-636,"y":-342,"font":{"size":30,"color":"#000000"},"color":"#97C2FC","label":"MENU","shape":"box","margin":{"top":15,"bottom":15,"left":15,"right":15},"widthConstraint":{"minimum":111},"fixed":false},{"id":"2c760279-0c75-4cd2-b61d-59f7f2477865","name":"RECEIPT","physics":false,"type":"entity-strong","backgroundColor":"#97C2FC","labelColor":"#000000","x":615,"y":-356,"font":{"size":30,"color":"#000000"},"color":"#97C2FC","label":"RECEIPT","shape":"box","margin":{"top":15,"bottom":15,"left":15,"right":15},"widthConstraint":{"minimum":111},"fixed":false},{"id":"66546fab-cf7e-45d8-9ab7-f112493aff2b","name":"ORDER","physics":false,"type":"entity-strong","backgroundColor":"#97C2FC","labelColor":"#000000","x":34,"y":-786,"font":{"size":30,"color":"#000000"},"color":"#97C2FC","label":"ORDER","shape":"box","margin":{"top":15,"bottom":15,"left":15,"right":15},"widthConstraint":{"minimum":111},"fixed":false},{"id":"0d29f136-4518-495d-9802-8df7e274d4af","name":"create","physics":false,"type":"relationship-normal","backgroundColor":"#97C2FC","labelColor":"#000000","x":308,"y":-992,"shape":"diamond","size":40,"color":"#97C2FC","fixed":false},{"id":"72b87a05-e740-4e25-b434-cb4400d304da","name":"create","physics":false,"type":"relationship-normal","backgroundColor":"#97C2FC","labelColor":"#000000","x":312,"y":-582,"shape":"diamond","size":40,"color":"#97C2FC","fixed":false},{"id":"45e68e76-fb86-4a76-b4c9-743123953a00","name":"order","physics":false,"type":"relationship-normal","backgroundColor":"#97C2FC","labelColor":"#000000","x":-285,"y":-341,"shape":"diamond","size":40,"color":"#97C2FC","fixed":false},{"id":"94873f31-9369-497b-a7d0-b63d4f033de5","name":"ACCOUNT","physics":false,"type":"entity-strong","backgroundColor":"#97C2FC","labelColor":"#000000","x":-626,"y":-1171,"font":{"size":30,"color":"#000000"},"color":"#97C2FC","label":"ACCOUNT","shape":"box","margin":{"top":15,"bottom":15,"left":15,"right":15},"widthConstraint":{"minimum":111},"fixed":false},{"id":"db839f88-2d8e-4c07-bfb4-990516b6ed03","name":"ORDER_ITEM","physics":false,"type":"entity-weak","backgroundColor":"#97C2FC","labelColor":"#000000","x":42,"y":-349,"font":{"size":30,"color":"#000000"},"color":"#97C2FC","label":"ORDER_ITEM","shape":"box","margin":{"top":15,"bottom":15,"left":15,"right":15},"widthConstraint":{"minimum":111},"fixed":false},{"id":"82ecae61-5734-402f-9b52-d0e7520ed864","name":"belong_to","physics":false,"type":"relationship-identify","backgroundColor":"#97C2FC","labelColor":"#000000","x":35,"y":-584,"shape":"diamond","size":40,"color":"#97C2FC","fixed":false},{"id":"f6ec8d4d-5b00-d1b8-225d-676352e7bcf0","name":"EMPLOYEE","physics":false,"type":"entity-strong","backgroundColor":"#97C2FC","labelColor":"#000000","x":-622,"y":-789,"font":{"size":30,"color":"#000000"},"color":"#97C2FC","label":"EMPLOYEE","shape":"box","margin":{"top":15,"bottom":15,"left":15,"right":15},"widthConstraint":{"minimum":111},"fixed":false},{"id":"ae09323e-88b6-6b93-8bb4-f8300a6ae522","name":"username","physics":false,"type":"attribute-normal","backgroundColor":"#97C2FC","labelColor":"#000000","x":-442,"y":-1206,"label":"username","shape":"ellipse","font":{"size":20,"color":"#000000"},"color":"#97C2FC","widthConstraint":{"minimum":111},"fixed":false},{"id":"869362e6-e7e0-0072-18a0-019199c8fd2f","name":"CUSTOMER_MEMBER","physics":false,"type":"entity-strong","backgroundColor":"#97C2FC","labelColor":"#000000","x":29,"y":-1188,"font":{"size":30,"color":"#000000"},"color":"#97C2FC","label":"CUSTOMER_MEMBER","shape":"box","margin":{"top":15,"bottom":15,"left":15,"right":15},"widthConstraint":{"minimum":111},"fixed":false},{"id":"5cdd629d-22a2-d0f3-8c48-790e5531647b","name":"CUSTOMER","physics":false,"type":"entity-strong","backgroundColor":"#97C2FC","labelColor":"#000000","x":605,"y":-1194,"font":{"size":30,"color":"#000000"},"color":"#97C2FC","label":"CUSTOMER","shape":"box","margin":{"top":15,"bottom":15,"left":15,"right":15},"widthConstraint":{"minimum":111},"fixed":false},{"id":"e059eeb9-52bf-4ed8-9559-0b3b32632594","name":"menu_id","physics":false,"type":"attribute-primary","backgroundColor":"#97C2FC","labelColor":"#000000","x":-491,"y":-403,"label":"menu_id","shape":"ellipse","font":{"size":20,"color":"#000000"},"color":"#97C2FC","widthConstraint":{"minimum":111},"fixed":false},{"id":"f85b83c5-1249-4bd8-a981-d29dd9277b40","name":"","physics":false,"type":"subtype-disjoint","backgroundColor":"#97C2FC","labelColor":"#000000","x":333,"y":-1185,"font":{"size":30,"color":"#000000"},"color":"#97C2FC","label":" d ","shape":"circle","margin":{"top":15,"bottom":15,"left":15,"right":15},"fixed":false},{"id":"af0ea123-22bc-4032-8e5d-ea66556aa396","name":"item_no","physics":false,"type":"attribute-partial","backgroundColor":"#97C2FC","labelColor":"#000000","x":-69,"y":-277,"label":"item_no","shape":"ellipse","font":{"size":20,"color":"#000000"},"color":"#97C2FC","widthConstraint":{"minimum":111},"fixed":false},{"id":"66561cec-8d19-40ad-bd61-a0b75e13e48d","name":"total_price","physics":false,"type":"attribute-derived","backgroundColor":"#97C2FC","labelColor":"#000000","x":-183,"y":-735,"label":"total_price","shape":"ellipse","font":{"size":20,"color":"#000000"},"color":{"background":"#cbe0fd","border":"#97C2FC"},"borderWidth":2,"shapeProperties":{"borderDashes":[5,5]},"widthConstraint":{"minimum":111},"fixed":false},{"id":"324683df-d76e-4444-a4cc-5d46c57d1af1","name":"account_id","physics":false,"type":"attribute-primary","backgroundColor":"#97C2FC","labelColor":"#000000","x":-437,"y":-1129,"label":"account_id","shape":"ellipse","font":{"size":20,"color":"#000000"},"color":"#97C2FC","widthConstraint":{"minimum":111},"fixed":false},{"id":"64ff9253-a190-4a1f-b5e0-7149d15e8313","name":"TABLE","physics":false,"type":"entity-strong","backgroundColor":"#97C2FC","labelColor":"#000000","x":609,"y":-782,"font":{"size":30,"color":"#000000"},"color":"#97C2FC","label":"TABLE","shape":"box","margin":{"top":15,"bottom":15,"left":15,"right":15},"widthConstraint":{"minimum":111},"fixed":false},{"id":"2938e3fd-5835-4711-89d1-b4d2e5e71807","name":"has","physics":false,"type":"relationship-normal","backgroundColor":"#97C2FC","labelColor":"#000000","x":307,"y":-783,"shape":"diamond","size":40,"color":"#97C2FC","fixed":false},{"id":"51a749ba-789c-4ccc-83f9-72d238f19c7b","name":"table_id","physics":false,"type":"attribute-primary","backgroundColor":"#97C2FC","labelColor":"#000000","x":768,"y":-820,"label":"table_id","shape":"ellipse","font":{"size":20,"color":"#000000"},"color":"#97C2FC","widthConstraint":{"minimum":111},"fixed":false},{"id":"9c8ac9fd-c036-4c50-8084-16efd162a755","name":"role","physics":false,"type":"attribute-normal","backgroundColor":"#97C2FC","labelColor":"#000000","x":-760,"y":-854,"label":"role","shape":"ellipse","font":{"size":20,"color":"#000000"},"color":"#97C2FC","widthConstraint":{"minimum":111},"fixed":false},{"id":"617110b2-d542-4450-af80-30e2bdc49a91","name":"receipt_no","physics":false,"type":"attribute-normal","backgroundColor":"#97C2FC","labelColor":"#000000","x":668,"y":-268,"label":"receipt_no","shape":"ellipse","font":{"size":20,"color":"#000000"},"color":"#97C2FC","widthConstraint":{"minimum":111},"fixed":false},{"id":"b6533fb2-b6b8-438c-8bcb-27cbfe6b2b2e","name":"total_price","physics":false,"type":"attribute-derived","backgroundColor":"#97C2FC","labelColor":"#000000","x":248,"y":-356,"label":"total_price","shape":"ellipse","font":{"size":20,"color":"#000000"},"color":{"background":"#cbe0fd","border":"#97C2FC"},"borderWidth":2,"shapeProperties":{"borderDashes":[5,5]},"widthConstraint":{"minimum":111},"fixed":false},{"id":"fed1b2e7-2702-5f47-7a9d-cf71af8c0aa2","name":"type","physics":false,"type":"attribute-normal","backgroundColor":"#97C2FC","labelColor":"#000000","x":799,"y":-1242,"label":"type","shape":"ellipse","font":{"size":20,"color":"#000000"},"color":"#97C2FC","widthConstraint":{"minimum":111},"fixed":false},{"id":"809ecf3c-1eaa-49a9-bf3b-9ba66001715a","name":"member_price","physics":false,"type":"attribute-normal","backgroundColor":"#97C2FC","labelColor":"#000000","x":-605,"y":-447,"label":"member_price","shape":"ellipse","font":{"size":20,"color":"#000000"},"color":"#97C2FC","widthConstraint":{"minimum":111},"fixed":false},{"id":"48d3fe25-f85a-44d7-8298-66c1cce1176d","name":"menu_price","physics":false,"type":"attribute-normal","backgroundColor":"#97C2FC","labelColor":"#000000","x":-591,"y":-240,"label":"menu_price","shape":"ellipse","font":{"size":20,"color":"#000000"},"color":"#97C2FC","widthConstraint":{"minimum":111},"fixed":false},{"id":"dde648ec-5dcd-4b2f-b97c-3f57c83776e5","name":"total_price","physics":false,"type":"attribute-normal","backgroundColor":"#97C2FC","labelColor":"#000000","x":768,"y":-392,"label":"total_price","shape":"ellipse","font":{"size":20,"color":"#000000"},"color":"#97C2FC","widthConstraint":{"minimum":111},"fixed":false},{"id":"607ae1b8-1d0e-9d2d-21f4-a93f61a9d9c5","name":"check_in","physics":false,"type":"attribute-normal","backgroundColor":"#97C2FC","labelColor":"#000000","x":727,"y":-1112,"label":"check_in","shape":"ellipse","font":{"size":20,"color":"#000000"},"color":"#97C2FC","widthConstraint":{"minimum":111},"fixed":false},{"id":"6389e739-c0e0-b565-4909-67df2b75f474","name":"check_out","physics":false,"type":"attribute-normal","backgroundColor":"#97C2FC","labelColor":"#000000","x":802,"y":-1169,"label":"check_out","shape":"ellipse","font":{"size":20,"color":"#000000"},"color":"#97C2FC","widthConstraint":{"minimum":111},"fixed":false},{"id":"e0ad3895-4976-021e-f56a-87577c49b0c3","name":"served_time","physics":false,"type":"attribute-normal","backgroundColor":"#97C2FC","labelColor":"#000000","x":-189,"y":-798,"label":"served_time","shape":"ellipse","font":{"size":20,"color":"#000000"},"color":"#97C2FC","widthConstraint":{"minimum":111},"fixed":false},{"id":"58e49259-c21f-9aaa-abbb-ab58b5a2af7f","name":"","physics":false,"type":"subtype-disjoint","backgroundColor":"#97C2FC","labelColor":"#000000","x":-315,"y":-977,"font":{"size":30,"color":"#000000"},"color":"#97C2FC","label":" d ","shape":"circle","margin":{"top":15,"bottom":15,"left":15,"right":15},"fixed":false},{"id":"3e610f20-6f4c-8b60-1ff1-55138856820c","name":"register_date","physics":false,"type":"attribute-normal","backgroundColor":"#97C2FC","labelColor":"#000000","x":112,"y":-1283,"label":"register_date","shape":"ellipse","font":{"size":20,"color":"#000000"},"color":"#97C2FC","widthConstraint":{"minimum":111},"fixed":false},{"id":"d57dee2c-386e-fc92-c046-ff990e689523","name":"expire_date","physics":false,"type":"attribute-normal","backgroundColor":"#97C2FC","labelColor":"#000000","x":-59,"y":-1274,"label":"expire_date","shape":"ellipse","font":{"size":20,"color":"#000000"},"color":"#97C2FC","widthConstraint":{"minimum":111},"fixed":false},{"id":"c82195de-70ba-22e6-0f85-f81567128ae2","name":"fname","physics":false,"type":"attribute-normal","backgroundColor":"#97C2FC","labelColor":"#000000","x":-789,"y":-1225,"label":"fname","shape":"ellipse","font":{"size":20,"color":"#000000"},"color":"#97C2FC","widthConstraint":{"minimum":111},"fixed":false},{"id":"859d461b-a3d1-a398-c637-5145db8d6f5f","name":"lname","physics":false,"type":"attribute-normal","backgroundColor":"#97C2FC","labelColor":"#000000","x":-789,"y":-1122,"label":"lname","shape":"ellipse","font":{"size":20,"color":"#000000"},"color":"#97C2FC","widthConstraint":{"minimum":111},"fixed":false},{"id":"b0bce24b-bd9b-2bfd-6906-a6c240b9ca64","name":"phone_number","physics":false,"type":"attribute-normal","backgroundColor":"#97C2FC","labelColor":"#000000","x":-631,"y":-1084,"label":"phone_number","shape":"ellipse","font":{"size":20,"color":"#000000"},"color":"#97C2FC","widthConstraint":{"minimum":111},"fixed":false},{"id":"037f8574-df5e-5504-83f8-dadcf4b170cd","name":"image_file_path","physics":false,"type":"attribute-normal","backgroundColor":"#97C2FC","labelColor":"#000000","x":-775,"y":-436,"label":"image_file_path","shape":"ellipse","font":{"size":20,"color":"#000000"},"color":"#97C2FC","widthConstraint":{"minimum":111},"fixed":false},{"id":"6aab1c36-1399-7ca9-4cf0-9175edef8271","name":"create_date","physics":false,"type":"attribute-normal","backgroundColor":"#97C2FC","labelColor":"#000000","x":-831,"y":-373,"label":"create_date","shape":"ellipse","font":{"size":20,"color":"#000000"},"color":"#97C2FC","widthConstraint":{"minimum":111},"fixed":false},{"id":"3a6ece00-9a3c-34fb-a78d-9d851aefdf68","name":"type","physics":false,"type":"attribute-normal","backgroundColor":"#97C2FC","labelColor":"#000000","x":-692,"y":-1273,"label":"type","shape":"ellipse","font":{"size":20,"color":"#000000"},"color":"#97C2FC","widthConstraint":{"minimum":111},"fixed":false},{"id":"2f4623ed-96ac-4575-af20-e0a1934a630c","name":"salary","physics":false,"type":"attribute-normal","backgroundColor":"#97C2FC","labelColor":"#000000","x":-823,"y":-783,"label":"salary","shape":"ellipse","font":{"size":20,"color":"#000000"},"color":"#97C2FC","widthConstraint":{"minimum":111},"fixed":false},{"id":"54a42597-8428-1003-cefe-ad7e296957f0","name":"gender","physics":false,"type":"attribute-normal","backgroundColor":"#97C2FC","labelColor":"#000000","x":-767,"y":-720,"label":"gender","shape":"ellipse","font":{"size":20,"color":"#000000"},"color":"#97C2FC","widthConstraint":{"minimum":111},"fixed":false},{"id":"8974e5ae-0ac6-2dec-cc3d-f2efe06afe62","name":"hire_date","physics":false,"type":"attribute-normal","backgroundColor":"#97C2FC","labelColor":"#000000","x":-457,"y":-737,"label":"hire_date","shape":"ellipse","font":{"size":20,"color":"#000000"},"color":"#97C2FC","widthConstraint":{"minimum":111},"fixed":false},{"id":"f7ca63ff-529e-4f1b-9298-4edf311d9968","name":"create_date","physics":false,"type":"attribute-normal","backgroundColor":"#97C2FC","labelColor":"#000000","x":783,"y":-315,"label":"create_date","shape":"ellipse","font":{"size":20,"color":"#000000"},"color":"#97C2FC","widthConstraint":{"minimum":111},"fixed":false},{"id":"48cc7329-dd65-b054-c5ea-2d1ce6283807","name":"ordering_time","physics":false,"type":"attribute-normal","backgroundColor":"#97C2FC","labelColor":"#000000","x":-75,"y":-914,"label":"ordering_time","shape":"ellipse","font":{"size":20,"color":"#000000"},"color":"#97C2FC","widthConstraint":{"minimum":111},"fixed":false},{"id":"3c341dfe-85ae-42c3-9dc6-747edb03074f","name":"status","physics":false,"type":"attribute-normal","backgroundColor":"#97C2FC","labelColor":"#000000","x":-158,"y":-860,"label":"status","shape":"ellipse","font":{"size":20,"color":"#000000"},"color":"#97C2FC","widthConstraint":{"minimum":111},"fixed":false},{"id":"561498a0-fc29-4b0a-a5a2-7dc38cdda3ab","name":"amount","physics":false,"type":"attribute-normal","backgroundColor":"#97C2FC","labelColor":"#000000","x":73,"y":-253,"label":"amount","shape":"ellipse","font":{"size":20,"color":"#000000"},"color":"#97C2FC","widthConstraint":{"minimum":111},"fixed":false},{"id":"74ce5b88-e71b-4d6f-b9e4-3eddb683c785","name":"price","physics":false,"type":"attribute-normal","backgroundColor":"#97C2FC","labelColor":"#000000","x":213,"y":-281,"label":"price","shape":"ellipse","font":{"size":20,"color":"#000000"},"color":"#97C2FC","widthConstraint":{"minimum":111},"fixed":false},{"id":"4915a029-23ec-459c-865d-5064156ff5e3","name":"receipt_id","physics":false,"type":"attribute-primary","backgroundColor":"#97C2FC","labelColor":"#000000","x":654,"y":-443,"label":"receipt_id","shape":"ellipse","font":{"size":20,"color":"#000000"},"color":"#97C2FC","widthConstraint":{"minimum":111},"fixed":false},{"id":"62be8685-e04d-0eb6-ef97-2ea4cd226412","name":"customer_id","physics":false,"type":"attribute-primary","backgroundColor":"#97C2FC","labelColor":"#000000","x":674,"y":-1284,"label":"customer_id","shape":"ellipse","font":{"size":20,"color":"#000000"},"color":"#97C2FC","widthConstraint":{"minimum":111},"fixed":false},{"id":"532b1023-4ab3-c77f-1e25-9f6e312edcd5","name":"employee_id","physics":false,"type":"attribute-primary","backgroundColor":"#97C2FC","labelColor":"#000000","x":-615,"y":-875,"label":"employee_id","shape":"ellipse","font":{"size":20,"color":"#000000"},"color":"#97C2FC","widthConstraint":{"minimum":111},"fixed":false},{"id":"f53f0967-3f65-8ef5-d344-73a92b355462","name":"address","physics":false,"type":"attribute-normal","backgroundColor":"#97C2FC","labelColor":"#000000","x":-439,"y":-806,"label":"address","shape":"ellipse","font":{"size":20,"color":"#000000"},"color":"#97C2FC","widthConstraint":{"minimum":111},"fixed":false},{"id":"c01c4ad5-75d1-14fd-40b3-f2ba458ad52b","name":"email","physics":false,"type":"attribute-normal","backgroundColor":"#97C2FC","labelColor":"#000000","x":-604,"y":-714,"label":"email","shape":"ellipse","font":{"size":20,"color":"#000000"},"color":"#97C2FC","widthConstraint":{"minimum":111},"fixed":false},{"id":"a2e172d9-f7d3-0bf9-ebf0-ab01904b1842","name":"quantity_item","physics":false,"type":"attribute-derived","backgroundColor":"#97C2FC","labelColor":"#000000","x":-58,"y":-698,"label":"quantity_item","shape":"ellipse","font":{"size":20,"color":"#000000"},"color":{"background":"#cbe0fd","border":"#97C2FC"},"borderWidth":2,"shapeProperties":{"borderDashes":[5,5]},"widthConstraint":{"minimum":111}},{"id":"0cc4f951-0a0a-492d-a00a-8da0ab0a0a67","name":"order_id","physics":false,"type":"attribute-primary","backgroundColor":"#97C2FC","labelColor":"#000000","x":71,"y":-894,"label":"order_id","shape":"ellipse","font":{"size":20,"color":"#000000"},"color":"#97C2FC","widthConstraint":{"minimum":111}},{"id":"3b8c4c32-d4d9-4c01-b80e-c0047c00445a","name":"status","physics":false,"type":"attribute-normal","backgroundColor":"#97C2FC","labelColor":"#000000","x":774,"y":-749,"label":"status","shape":"ellipse","font":{"size":20,"color":"#000000"},"color":"#97C2FC","widthConstraint":{"minimum":111}},{"id":"92ac5b38-cb68-4249-90aa-a1747a4c1cf4","name":"TOKEN","physics":false,"type":"entity-strong","backgroundColor":"#97C2FC","labelColor":"#000000","x":-1256,"y":-1175,"font":{"size":30,"color":"#000000"},"color":"#97C2FC","label":"TOKEN","shape":"box","margin":{"top":15,"bottom":15,"left":15,"right":15},"widthConstraint":{"minimum":111}},{"id":"7f92282a-3f0a-48cc-924e-946fabb8c66f","name":"end_date","physics":false,"type":"attribute-normal","backgroundColor":"#97C2FC","labelColor":"#000000","x":-1160,"y":-1106,"label":"end_date","shape":"ellipse","font":{"size":20,"color":"#000000"},"color":"#97C2FC","widthConstraint":{"minimum":111}},{"id":"bcfd1a5f-523d-4d92-80ec-f0eed449a9af","name":"has","physics":false,"type":"relationship-normal","backgroundColor":"#97C2FC","labelColor":"#000000","x":-1003,"y":-1173,"shape":"diamond","size":40,"color":"#97C2FC"},{"id":"08243f0b-a833-0867-9e84-152758ef55e4","name":"password","physics":false,"type":"attribute-normal","backgroundColor":"#97C2FC","labelColor":"#000000","x":-545,"y":-1261,"label":"password","shape":"ellipse","font":{"size":20,"color":"#000000"},"color":"#97C2FC","widthConstraint":{"minimum":111}},{"id":"49a5f782-0018-455a-a5ad-d44a2741d264","name":"menu_status","physics":false,"type":"attribute-normal","backgroundColor":"#97C2FC","labelColor":"#000000","x":-750,"y":-239,"label":"menu_status","shape":"ellipse","font":{"size":20,"color":"#000000"},"color":"#97C2FC","widthConstraint":{"minimum":111}},{"id":"ab7708a5-7353-4d9c-b3d8-c35b557a1b53","name":"menu_name","physics":false,"type":"attribute-normal","backgroundColor":"#97C2FC","labelColor":"#000000","x":-484,"y":-290,"label":"menu_name","shape":"ellipse","font":{"size":20,"color":"#000000"},"color":"#97C2FC","widthConstraint":{"minimum":111}},{"id":"44eb67c9-395b-3a06-a413-95d18dc438aa","name":"delete_date","physics":false,"type":"attribute-normal","backgroundColor":"#97C2FC","labelColor":"#000000","x":-831,"y":-304,"label":"delete_date","shape":"ellipse","font":{"size":20,"color":"#000000"},"color":"#97C2FC","widthConstraint":{"minimum":111}},{"id":"cce09cc4-b73b-5006-aa17-6c3ddd261eaf","name":"token_id","physics":false,"type":"attribute-primary","backgroundColor":"#97C2FC","labelColor":"#000000","x":-1336,"y":-1241,"label":"token_id","shape":"ellipse","font":{"size":20,"color":"#000000"},"color":"#97C2FC","widthConstraint":{"minimum":111}},{"id":"ed2634cf-258e-abab-bd9b-d208818318d0","name":"start_date","physics":false,"type":"attribute-normal","backgroundColor":"#97C2FC","labelColor":"#000000","x":-1347,"y":-1106,"label":"start_date","shape":"ellipse","font":{"size":20,"color":"#000000"},"color":"#97C2FC","widthConstraint":{"minimum":111}},{"id":"969c3610-06d3-2c5b-1a8d-50435b7d260f","name":"token","physics":false,"type":"attribute-normal","backgroundColor":"#97C2FC","labelColor":"#000000","x":-1177,"y":-1243,"label":"token","shape":"ellipse","font":{"size":20,"color":"#000000"},"color":"#97C2FC","widthConstraint":{"minimum":111}}],"edges":[{"from":"1453b11a-006e-4670-9fb7-7f8467904965","to":"e059eeb9-52bf-4ed8-9559-0b3b32632594","id":"505ada8b-96cf-4115-9eeb-c90ae840982a","type":"optional","length":200,"font":{"align":"top","size":20}},{"from":"1453b11a-006e-4670-9fb7-7f8467904965","to":"49a5f782-0018-455a-a5ad-d44a2741d264","id":"e57d21a7-5f9f-4acd-985d-f9205693871d","type":"optional","length":200,"font":{"align":"top","size":20}},{"from":"1453b11a-006e-4670-9fb7-7f8467904965","to":"48d3fe25-f85a-44d7-8298-66c1cce1176d","id":"756f58de-01a4-4148-a0cf-e191165910ca","type":"optional","length":200,"font":{"align":"top","size":20}},{"from":"1453b11a-006e-4670-9fb7-7f8467904965","to":"ab7708a5-7353-4d9c-b3d8-c35b557a1b53","id":"b870f95f-adb7-4968-9668-29c74d6340ed","type":"optional","length":200,"font":{"align":"top","size":20}},{"from":"2c760279-0c75-4cd2-b61d-59f7f2477865","to":"f7ca63ff-529e-4f1b-9298-4edf311d9968","id":"4084594a-20b9-4e87-a25d-f03557115e2b","type":"optional","length":200,"font":{"align":"top","size":20}},{"from":"2c760279-0c75-4cd2-b61d-59f7f2477865","to":"dde648ec-5dcd-4b2f-b97c-3f57c83776e5","id":"954c9978-594d-43c5-b1f5-71751ca246f9","type":"optional","length":200,"font":{"align":"top","size":20}},{"from":"2c760279-0c75-4cd2-b61d-59f7f2477865","to":"4915a029-23ec-459c-865d-5064156ff5e3","id":"2767ba82-a65f-4743-85e3-e35432c17b25","type":"optional","length":200,"font":{"align":"top","size":20}},{"from":"66546fab-cf7e-45d8-9ab7-f112493aff2b","to":"0cc4f951-0a0a-492d-a00a-8da0ab0a0a67","id":"e182dd36-56f7-494d-a5ca-d2976f0a2200","type":"optional","length":200,"font":{"align":"top","size":20}},{"from":"db839f88-2d8e-4c07-bfb4-990516b6ed03","to":"af0ea123-22bc-4032-8e5d-ea66556aa396","id":"aaf2e857-86bc-4df3-a1dd-74bdd0c71a96","type":"optional","length":200,"font":{"align":"top","size":20}},{"from":"db839f88-2d8e-4c07-bfb4-990516b6ed03","to":"b6533fb2-b6b8-438c-8bcb-27cbfe6b2b2e","id":"d2a26ff5-57b6-47b3-985f-949560a3c647","type":"optional","length":200,"font":{"align":"top","size":20}},{"from":"66546fab-cf7e-45d8-9ab7-f112493aff2b","to":"66561cec-8d19-40ad-bd61-a0b75e13e48d","id":"d5045925-1f66-43d4-b39f-2602184d160f","type":"optional","length":200,"font":{"align":"top","size":20}},{"from":"66546fab-cf7e-45d8-9ab7-f112493aff2b","type":"optional","to":"82ecae61-5734-402f-9b52-d0e7520ed864","label":"1","length":200,"font":{"align":"top","size":20},"id":"a78a7df2-0723-4e05-b8f2-31da8f781d53","smooth":false},{"from":"db839f88-2d8e-4c07-bfb4-990516b6ed03","type":"mandatory","to":"82ecae61-5734-402f-9b52-d0e7520ed864","label":"N","length":200,"font":{"align":"top","size":20},"id":"263e4896-235c-4ac2-8e00-eaff804c4073","smooth":false},{"from":"f6ec8d4d-5b00-d1b8-225d-676352e7bcf0","to":"532b1023-4ab3-c77f-1e25-9f6e312edcd5","id":"9cc87f35-d158-4810-a680-b931c9e19a0a","type":"optional","length":200,"font":{"align":"top","size":20}},{"from":"f6ec8d4d-5b00-d1b8-225d-676352e7bcf0","to":"f53f0967-3f65-8ef5-d344-73a92b355462","id":"a41c100b-08cd-44e4-820a-6b0e02cec81e","type":"optional","length":200,"font":{"align":"top","size":20}},{"from":"94873f31-9369-497b-a7d0-b63d4f033de5","to":"ae09323e-88b6-6b93-8bb4-f8300a6ae522","id":"f60c2b8f-a4f4-43fb-bcf6-c566b4964b9c","type":"optional","length":200,"font":{"align":"top","size":20}},{"from":"94873f31-9369-497b-a7d0-b63d4f033de5","to":"08243f0b-a833-0867-9e84-152758ef55e4","id":"91782afb-ab78-4737-820a-3313e4be159d","type":"optional","length":200,"font":{"align":"top","size":20}},{"from":"5cdd629d-22a2-d0f3-8c48-790e5531647b","to":"62be8685-e04d-0eb6-ef97-2ea4cd226412","id":"2732cc5f-e3e9-4afa-975a-31168b6fece9","type":"optional","length":200,"font":{"align":"top","size":20}},{"from":"5cdd629d-22a2-d0f3-8c48-790e5531647b","to":"fed1b2e7-2702-5f47-7a9d-cf71af8c0aa2","id":"872d67de-bea7-4677-80f9-d4db877b3d5d","type":"optional","length":200,"font":{"align":"top","size":20}},{"from":"66546fab-cf7e-45d8-9ab7-f112493aff2b","to":"a2e172d9-f7d3-0bf9-ebf0-ab01904b1842","id":"9e711a85-d9ad-4229-a3c9-338eda4e02a6","type":"optional","length":200,"font":{"align":"top","size":20}},{"from":"66546fab-cf7e-45d8-9ab7-f112493aff2b","type":"optional","to":"72b87a05-e740-4e25-b434-cb4400d304da","label":"1","length":200,"font":{"align":"top","size":20},"id":"c051aa6c-0a69-49ce-8b18-0c6fce874100","smooth":false},{"from":"2c760279-0c75-4cd2-b61d-59f7f2477865","type":"mandatory","to":"72b87a05-e740-4e25-b434-cb4400d304da","label":"1","length":200,"font":{"align":"top","size":20},"id":"3a6c3d2f-bc66-4685-85ab-e45940266770","smooth":false},{"from":"f85b83c5-1249-4bd8-a981-d29dd9277b40","to":"869362e6-e7e0-0072-18a0-019199c8fd2f","id":"0e9e09c0-efec-4135-b93e-8fa34c977f89","type":"subtype","length":200,"font":{"align":"top","size":20}},{"from":"5cdd629d-22a2-d0f3-8c48-790e5531647b","to":"f85b83c5-1249-4bd8-a981-d29dd9277b40","id":"c2691bf6-15a4-4622-83c5-a1119435dbd5","type":"optional","length":200,"font":{"align":"top","size":20}},{"from":"db839f88-2d8e-4c07-bfb4-990516b6ed03","to":"561498a0-fc29-4b0a-a5a2-7dc38cdda3ab","id":"c20d9610-9cc5-459d-aef6-00e1aa3abd10","type":"optional","length":200,"font":{"align":"top","size":20}},{"from":"66546fab-cf7e-45d8-9ab7-f112493aff2b","to":"3c341dfe-85ae-42c3-9dc6-747edb03074f","id":"9dc74cd7-9bb2-4c57-948c-a338f4843edf","type":"optional","length":200,"font":{"align":"top","size":20}},{"from":"2c760279-0c75-4cd2-b61d-59f7f2477865","to":"617110b2-d542-4450-af80-30e2bdc49a91","id":"cefcef55-7094-4218-9ab6-a82554667774","type":"optional","length":200,"font":{"align":"top","size":20}},{"from":"1453b11a-006e-4670-9fb7-7f8467904965","to":"809ecf3c-1eaa-49a9-bf3b-9ba66001715a","id":"96dd7be1-1be6-4eaa-bee7-fd01a833b540","type":"optional","length":200,"font":{"align":"top","size":20}},{"from":"f6ec8d4d-5b00-d1b8-225d-676352e7bcf0","to":"9c8ac9fd-c036-4c50-8084-16efd162a755","id":"1bc94cb7-5cae-425a-8372-b1ae728f77db","type":"optional","length":200,"font":{"align":"top","size":20}},{"from":"94873f31-9369-497b-a7d0-b63d4f033de5","to":"324683df-d76e-4444-a4cc-5d46c57d1af1","id":"128cd8af-adac-403b-95e8-4e3435e60cb2","type":"optional","length":200,"font":{"align":"top","size":20}},{"from":"64ff9253-a190-4a1f-b5e0-7149d15e8313","to":"51a749ba-789c-4ccc-83f9-72d238f19c7b","id":"9929fc9f-ffea-40b6-a388-e94731d8b186","type":"optional","length":200,"font":{"align":"top","size":20}},{"from":"64ff9253-a190-4a1f-b5e0-7149d15e8313","to":"3b8c4c32-d4d9-4c01-b80e-c0047c00445a","id":"429609f6-61d6-4673-9fd4-815a5debdf23","type":"optional","length":200,"font":{"align":"top","size":20}},{"from":"f6ec8d4d-5b00-d1b8-225d-676352e7bcf0","to":"2f4623ed-96ac-4575-af20-e0a1934a630c","id":"11095b19-7313-474c-ba88-dd617b3a1936","type":"optional","length":200,"font":{"align":"top","size":20}},{"from":"1453b11a-006e-4670-9fb7-7f8467904965","type":"optional","to":"45e68e76-fb86-4a76-b4c9-743123953a00","label":"1","length":200,"font":{"align":"top","size":20},"id":"0907605c-ca57-498c-bae3-764dfd9428e1","smooth":false},{"from":"db839f88-2d8e-4c07-bfb4-990516b6ed03","type":"mandatory","to":"45e68e76-fb86-4a76-b4c9-743123953a00","label":"N","length":200,"font":{"align":"top","size":20},"id":"f9b642d2-2cd6-496d-88a1-bcd249e0ce7f","smooth":false},{"from":"5cdd629d-22a2-d0f3-8c48-790e5531647b","type":"optional","to":"0d29f136-4518-495d-9802-8df7e274d4af","label":"1","length":200,"font":{"align":"top","size":20},"id":"67cd15a1-876f-405a-af4f-4d338f480120","smooth":false},{"from":"66546fab-cf7e-45d8-9ab7-f112493aff2b","type":"mandatory","to":"0d29f136-4518-495d-9802-8df7e274d4af","label":"N","length":200,"font":{"align":"top","size":20},"id":"3a04ea60-9c60-4293-b8b1-b03c4057be69","smooth":false},{"from":"db839f88-2d8e-4c07-bfb4-990516b6ed03","to":"74ce5b88-e71b-4d6f-b9e4-3eddb683c785","id":"47aaa161-8782-448a-afd0-eba26d8fc384","type":"optional","length":200,"font":{"align":"top","size":20}},{"from":"5cdd629d-22a2-d0f3-8c48-790e5531647b","to":"607ae1b8-1d0e-9d2d-21f4-a93f61a9d9c5","id":"e1624062-965f-492d-848c-65d540d49ec3","type":"optional","length":200,"font":{"align":"top","size":20}},{"from":"5cdd629d-22a2-d0f3-8c48-790e5531647b","to":"6389e739-c0e0-b565-4909-67df2b75f474","id":"baef3328-1aea-4e48-adfc-a1f86d41d262","type":"optional","length":200,"font":{"align":"top","size":20}},{"from":"66546fab-cf7e-45d8-9ab7-f112493aff2b","to":"48cc7329-dd65-b054-c5ea-2d1ce6283807","id":"9715d97d-c29c-49cc-94ad-efd34ffa9add","type":"optional","length":200,"font":{"align":"top","size":20}},{"from":"66546fab-cf7e-45d8-9ab7-f112493aff2b","to":"e0ad3895-4976-021e-f56a-87577c49b0c3","id":"a3bdba7a-8171-42e4-8e54-386c4b2961d1","type":"optional","length":200,"font":{"align":"top","size":20}},{"from":"58e49259-c21f-9aaa-abbb-ab58b5a2af7f","to":"f6ec8d4d-5b00-d1b8-225d-676352e7bcf0","id":"729869d0-862e-4163-bba7-fb09f9fb15cd","type":"subtype","length":200,"font":{"align":"top","size":20}},{"from":"58e49259-c21f-9aaa-abbb-ab58b5a2af7f","to":"869362e6-e7e0-0072-18a0-019199c8fd2f","id":"83231074-96be-4028-8f5f-e16543918f64","type":"subtype","length":200,"font":{"align":"top","size":20}},{"from":"94873f31-9369-497b-a7d0-b63d4f033de5","to":"58e49259-c21f-9aaa-abbb-ab58b5a2af7f","id":"f3bf2514-6379-4d2b-8a5d-f28bfdd57d91","type":"mandatory","length":200,"font":{"align":"top","size":20}},{"from":"94873f31-9369-497b-a7d0-b63d4f033de5","to":"3a6ece00-9a3c-34fb-a78d-9d851aefdf68","id":"2f91dd4d-78e0-4e26-b324-28a2e4c486b3","type":"optional","length":200,"font":{"align":"top","size":20}},{"from":"869362e6-e7e0-0072-18a0-019199c8fd2f","to":"3e610f20-6f4c-8b60-1ff1-55138856820c","id":"cdd42ca9-79c3-4aed-8874-72aa8e0708d9","type":"optional","length":200,"font":{"align":"top","size":20}},{"from":"869362e6-e7e0-0072-18a0-019199c8fd2f","to":"d57dee2c-386e-fc92-c046-ff990e689523","id":"c611d018-cdbe-4dca-8f66-48a507129471","type":"optional","length":200,"font":{"align":"top","size":20}},{"from":"94873f31-9369-497b-a7d0-b63d4f033de5","to":"c82195de-70ba-22e6-0f85-f81567128ae2","id":"a9e9a8be-301a-45d7-9ed5-6613ca593398","type":"optional","length":200,"font":{"align":"top","size":20}},{"from":"94873f31-9369-497b-a7d0-b63d4f033de5","to":"859d461b-a3d1-a398-c637-5145db8d6f5f","id":"2c15d295-c1ef-491c-8c09-29f2d1e81495","type":"optional","length":200,"font":{"align":"top","size":20}},{"from":"94873f31-9369-497b-a7d0-b63d4f033de5","to":"b0bce24b-bd9b-2bfd-6906-a6c240b9ca64","id":"484fb961-8acc-4856-9b9b-2d8a7ae7acb9","type":"optional","length":200,"font":{"align":"top","size":20}},{"from":"64ff9253-a190-4a1f-b5e0-7149d15e8313","type":"optional","to":"2938e3fd-5835-4711-89d1-b4d2e5e71807","label":"1","length":200,"font":{"align":"top","size":20},"id":"14f97268-5682-4a38-9354-9cf00625427d","smooth":false},{"from":"66546fab-cf7e-45d8-9ab7-f112493aff2b","type":"mandatory","to":"2938e3fd-5835-4711-89d1-b4d2e5e71807","label":"N","length":200,"font":{"align":"top","size":20},"id":"0c436fc1-f9ce-4bab-a567-e0dfc51313a7","smooth":false},{"from":"1453b11a-006e-4670-9fb7-7f8467904965","to":"037f8574-df5e-5504-83f8-dadcf4b170cd","id":"9fdc0ec7-e944-48f3-928b-56256988401c","type":"optional","length":200,"font":{"align":"top","size":20}},{"from":"1453b11a-006e-4670-9fb7-7f8467904965","to":"6aab1c36-1399-7ca9-4cf0-9175edef8271","id":"17eee56c-5f72-4021-8a5f-b9c450fda8d8","type":"optional","length":200,"font":{"align":"top","size":20}},{"from":"f6ec8d4d-5b00-d1b8-225d-676352e7bcf0","to":"54a42597-8428-1003-cefe-ad7e296957f0","id":"0eef832e-d45c-46da-93ab-2e630d0194cd","type":"optional","length":200,"font":{"align":"top","size":20}},{"from":"f6ec8d4d-5b00-d1b8-225d-676352e7bcf0","to":"8974e5ae-0ac6-2dec-cc3d-f2efe06afe62","id":"9fb223eb-7724-4e9e-ad85-bc2649aca12c","type":"optional","length":200,"font":{"align":"top","size":20}},{"from":"f6ec8d4d-5b00-d1b8-225d-676352e7bcf0","to":"c01c4ad5-75d1-14fd-40b3-f2ba458ad52b","id":"319ee108-3906-4206-af61-216eee0eaf74","type":"optional","length":200,"font":{"align":"top","size":20}},{"from":"92ac5b38-cb68-4249-90aa-a1747a4c1cf4","to":"cce09cc4-b73b-5006-aa17-6c3ddd261eaf","id":"9f47f744-0d99-4126-9646-df7fd7b03329","type":"optional","length":200,"font":{"align":"top","size":20}},{"from":"92ac5b38-cb68-4249-90aa-a1747a4c1cf4","to":"969c3610-06d3-2c5b-1a8d-50435b7d260f","id":"ab595e58-9033-4028-a6ab-de0660edeecb","type":"optional","length":200,"font":{"align":"top","size":20}},{"from":"92ac5b38-cb68-4249-90aa-a1747a4c1cf4","to":"ed2634cf-258e-abab-bd9b-d208818318d0","id":"ca3785b5-02a4-47ac-84c6-1609ca1106e8","type":"optional","length":200,"font":{"align":"top","size":20}},{"from":"92ac5b38-cb68-4249-90aa-a1747a4c1cf4","to":"7f92282a-3f0a-48cc-924e-946fabb8c66f","id":"b52d7d99-fe4a-44d3-bdb8-76da25145f7a","type":"optional","length":200,"font":{"align":"top","size":20}},{"from":"1453b11a-006e-4670-9fb7-7f8467904965","to":"44eb67c9-395b-3a06-a413-95d18dc438aa","id":"37f940a2-c46a-4602-bbec-d3a840cf63da","type":"optional","length":200,"font":{"align":"top","size":20}},{"from":"92ac5b38-cb68-4249-90aa-a1747a4c1cf4","type":"mandatory","to":"bcfd1a5f-523d-4d92-80ec-f0eed449a9af","label":"N","length":200,"font":{"align":"top","size":20},"id":"af4c7f67-2a50-44b9-bfe0-49b662dc62b5","smooth":false},{"from":"94873f31-9369-497b-a7d0-b63d4f033de5","type":"optional","to":"bcfd1a5f-523d-4d92-80ec-f0eed449a9af","label":"1","length":200,"font":{"align":"top","size":20},"id":"732cab23-a797-462a-9d12-6c8ce2da808f","smooth":false}],"date":"2022-04-22T05:09:48.848Z","logger":["ICxYp2Q5k8nC0NaCsP9I7xUWLQ+Y3hvhV0NwTJCZRPHqiS9Mkmr/VEdLmB+S8Xkt5uUlSJkK4WgEG0E8x3AVNSQab86Ky/HKSdx4O5poHABQeyV3+fU9jTmBBWTVqRQDhTzuzKefDH/2NKpOFryoKbSDUQ0JMTp5QxXF9ttIKy4=","U/qxGd/yWy2cbZZUdAg3adt4YULPxyfWITdZGLFbqjI12wLERxlU7KSMiu0d05FWu5/PRbUzXNCTRGo1loCRcnU9Z4ogn/1VJaxTDecWvehMzau85GHJzOpeNx7EII2O/x6aia2QOjYu+LrzCENssIgU4X4Z9kv28FEXFrMUEhQ=","CogftU4aCmRZaTUUY9CC2BtoaUsao+5jWxtEYE4S8p02tforsXNkUTBHGt3Rfy7C3AziwUbD2mPyIkjRRppmgYgX4vX3vZZgh4sq4fgBFSxn5Tf0NX3bs4dw6Hj5qCY7B9pLDQgucToG4Z8X2yu8Vpg3yF2jRs1nnrQ9ySW3K/Q=","SiaWIpmeWYv71whIYfrPQTj3pab44i79w/kgXmqt0u4M46L8L+lZereyefjY/9HXrGuYfJDdPYsQnRn2WNRYhOHFXsGRLKVZ3BBI66W/raE/UxJK9eQ+PPDpfN2tN1D3f2eTBSh7kK1erN+3vUBp13xMNuivZ9qCdZnZjkRNFZM=","Mb9IaMYu6g9Aibq88i9zk63FCTJ+i9dC26AU8XuU2AzwvzXym38kwCEmLQM7khdCtdmhZrMBx+drfuaEnUHI9Gsl8gHdnLxvYWuX7CWWt9mgXKsCE+AUiXnGYTGkOvmO8mRqBDnDsx91fQn/4HSee6VqDzfzqrd8/zdsjCxPXEw=","PsG2gZnRH7MDcBBeuWNHE89K0Jt17U2oVR8oZ93+k5DvvGim+GA/IvL5Ufp9B88VOr4OWfiwJMY8n7esfE6CufLDh4qyW84VuXdCzwrqQo/YQmOKu4V9+YyfnCJaoSHWdzVUd5GYxTGeruDfM/bB6YdLfY8r3aIoGuYXIMSnXuc=","S0ezSFYS3ocx4UpWpLogzefSTwW94lmqVoEw5VShOSXUe9ykSATYSG4ug9kCcSTAHpZAa0C/fu6KvTiTNBadksmW+MEu3ixNSxcgnc1ucIb1/Ik8QQ/MfDwfDy8B29Vc8kWePZM0ubD5wlV+o/gy+ANmJg6mZyXo5ghOm/UdvTI=","KWPxB5oRpQ4PRi/vaT+Ciz/w+7ux6RpKSmHNyPK+cleBJ9LJOuKlIv9Xi8MAIzzo0ddPNcwFGBEkrTPlswYeKHxFKzs8cgLLfPSDFBK1aUT0SmtZHwpaITjLa+go5vY93ukXVyMPAXnAqdQ9VWZK2sk+6YgH0RaXxbIJTPXJGn0=","DwYpR8+hKUKXnkFXSam0LZzexO45oB73RRQXm43tjzgZ1AX1KwusC98+WvFg+v7sgEPOBxnG/NSqC41R6JRqEHWfcEh+W7K69dbGC5qcNHvsMYkPiRCGDHUDneyc0sFUA1jhoXdQqVrSm1Arr4E1ZpyGrtE1W+Jcs8xlBK23qxo=","XxnCoW39KT2o5+rtQWH+feN8TNe7FvVBQ+WvaPh+jO1XWHNUkHGh3uU27smgb0hs0Y7bYjTlciU65uKrbe1B+tS+D22IsDjbfcqHi0bEkyIiz4NqHUzWNz8rjJwQow0kEwDkMARREcqwLFzqH80sLxJZLT5HQGizb0hYu03eEyk=","RCPTxfJTCZAe83qzXjGfB6ojGWKbYL43yt6DhFICO9tud0K+BR+Qp5McGR1dBqjX3+W9hSBHBX1ZXsVs+MgE+tYe8HCuqcZeyQzKR0jAoeiMtmstd1/SURSaEk5reCY4svT+LHOvZZ64ZcZrmRJ1H2JKTWxhnyjnNwau/EXpUo0=","ZqTyxQf283GLQ87gR6MydqiptCLOOXL1UJosVUHTQPZGmhiWqc0LVX6JyQVXVERebsyyh2aB57v3gmR6gYPQsry34ZID8ujgP1UYsThbyL/Q/5GBF9iYkwFjMonprnBdWwDJTARrGYQ414YtJUFVM5bSbuDU1wGgPKYV2WfkTBc=","cJIYuXSxi4/gQmfuu9uh5FTkY4LPRVpoggtRE9oTaytnOnDm1/OX6nt09+qKxZiT9o8GqolI+wvsNuBgW5iy8PT09DVV+aFf+DmvJRCTR9Cb/tnb5m5pDPtjGKpDt45aiJaT2GExMtMZsXru/W0p1mnsCEtq7xVVj97ymR2Nl1g=","eD36mZaTkNphnc8O1D3Q/KLeXglQlM/zMvnzrpx8ZwCRbcaHVyw/PNAEGfCMVzdsWLn4vff22CwQyEXGBw5/9FMZpcu0ULfNDELty8LeuEcblLieAphGzSQqUSMjTHyLPiSLsfiUDrEx0eCzGRVdt8jWKV/1CTqjzM18HEpmoOs=","EWyKtLO3sy4gZ5sz9Hll1JXJrF8Znsxtk4HsIubcDSiEYnvKLHZQd3jfAjru7iBEE1lQbblgnC2hEIUWgohiHXBhUiCD9YPU3uKqjbtLBsQ/EVy0Ol597J64EAkfvDWpT9uhYTKD7szUaI8rB8q56fFpCQfwJki/D+NzFJ/FpaI=","az6Fd0r+Zf5fXcZkhyjpRrdRpSUM3e223JjlK465J+ogfNZcOmBSbhNgwnOtr/0YRuZ28qpICCE/RtykdPjO5uJFEBkKwI1FujQITI+HFNSBW045KC2BqQGSjawLKxdc55SLh7UPcFk4zGH528guJUcWwO1+lb9ZZ4ZyGswIp/s="]}